{
  "quotes": [
    { "id": 1, "text": "Every day is a second chance." },
    { "id": 2, "text": "Small steps every day lead to big results." },
    { "id": 3, "text": "Your only limit is your mindset." },
    { "id": 4, "text": "Dream it. Believe it. Build it." },
    { "id": 5, "text": "The struggle today is the strength tomorrow." },
    { "id": 6, "text": "Focus on progress, not perfection." },
    { "id": 7, "text": "Don’t wait for opportunity. Create it." },
    { "id": 8, "text": "Discipline beats motivation." },
    { "id": 9, "text": "You are stronger than you think." },
    { "id": 10, "text": "Consistency is the real key to success." },

    { "id": 11, "text": "Hard work always pays off." },
    { "id": 12, "text": "Stay patient and trust the process." },
    { "id": 13, "text": "Progress is still progress, no matter how small." },
    { "id": 14, "text": "Make today count." },
    { "id": 15, "text": "Your future is created by what you do today." },
    { "id": 16, "text": "Success begins with self-belief." },
    { "id": 17, "text": "Growth starts outside your comfort zone." },
    { "id": 18, "text": "Be consistent, not perfect." },
    { "id": 19, "text": "Simplicity is the ultimate sophistication." },
    { "id": 20, "text": "Great things take time." },

    { "id": 21, "text": "Stay hungry for success." },
    { "id": 22, "text": "Keep going even when it gets tough." },
    { "id": 23, "text": "Your effort today shapes your tomorrow." },
    { "id": 24, "text": "Work in silence, let success speak." },
    { "id": 25, "text": "Failure is part of the journey." },
    { "id": 26, "text": "A calm mind is a powerful mind." },
    { "id": 27, "text": "Take control of your own story." },
    { "id": 28, "text": "Never stop improving." },
    { "id": 29, "text": "Success is built one day at a time." },
    { "id": 30, "text": "Your habits shape your future." },

    { "id": 31, "text": "Believe in slow but steady growth." },
    { "id": 32, "text": "Strong minds create strong lives." },
    { "id": 33, "text": "Your goals deserve your focus." },
    { "id": 34, "text": "Doubt kills more dreams than failure." },
    { "id": 35, "text": "Show up for yourself every day." },
    { "id": 36, "text": "Build discipline and freedom will follow." },
    { "id": 37, "text": "Your mindset determines your direction." },
    { "id": 38, "text": "Small wins lead to big victories." },
    { "id": 39, "text": "Stay consistent even when no one is watching." },
    { "id": 40, "text": "Success loves preparation." },

    { "id": 41, "text": "Patience turns effort into results." },
    { "id": 42, "text": "Be proud of every step you take." },
    { "id": 43, "text": "One focused hour beats ten distracted ones." },
    { "id": 44, "text": "Energy flows where attention goes." },
    { "id": 45, "text": "Progress over excuses." },
    { "id": 46, "text": "Do something today your future self will thank you for." },
    { "id": 47, "text": "Your goals do not care how you feel." },
    { "id": 48, "text": "Success is built through daily action." },
    { "id": 49, "text": "Confidence grows with action." },
    { "id": 50, "text": "You learn more from failures than success." },

    { "id": 51, "text": "Your time is your most valuable asset." },
    { "id": 52, "text": "Discomfort is the price of growth." },
    { "id": 53, "text": "Focus on what you can control." },
    { "id": 54, "text": "Every effort compounds." },
    { "id": 55, "text": "Consistency beats intensity." },
    { "id": 56, "text": "Don't rush the process." },
    { "id": 57, "text": "Commit to getting better every day." },
    { "id": 58, "text": "Progress requires patience." },
    { "id": 59, "text": "The work you avoid today becomes tomorrow’s regret." },
    { "id": 60, "text": "A focused mind is a powerful weapon." },

    { "id": 61, "text": "Success is earned, not given." },
    { "id": 62, "text": "Your actions define your future." },
    { "id": 63, "text": "Be disciplined even when motivation fades." },
    { "id": 64, "text": "Growth feels uncomfortable at first." },
    { "id": 65, "text": "Your effort is never wasted." },
    { "id": 66, "text": "Hard times build strong character." },
    { "id": 67, "text": "Stay focused on your own lane." },
    { "id": 68, "text": "The process is just as important as the goal." },
    { "id": 69, "text": "Success rewards those who stay consistent." },
    { "id": 70, "text": "Your potential is greater than your doubts." },

    { "id": 71, "text": "Every choice you make shapes your life." },
    { "id": 72, "text": "Commit first, results come later." },
    { "id": 73, "text": "Discipline creates freedom." },
    { "id": 74, "text": "You become what you repeatedly do." },
    { "id": 75, "text": "Clarity brings confidence." },
    { "id": 76, "text": "Strength is built through struggle." },
    { "id": 77, "text": "Your future depends on today's effort." },
    { "id": 78, "text": "Consistency shapes destiny." },
    { "id": 79, "text": "Focus brings results." },
    { "id": 80, "text": "Your greatest rival is yesterday’s version of you." },

    { "id": 81, "text": "Progress grows when excuses shrink." },
    { "id": 82, "text": "Action cures fear." },
    { "id": 83, "text": "Your dreams demand discipline." },
    { "id": 84, "text": "Small daily habits build massive outcomes." },
    { "id": 85, "text": "Effort creates opportunity." },
    { "id": 86, "text": "Your mindset sets your ceiling." },
    { "id": 87, "text": "The path gets clearer as you walk it." },
    { "id": 88, "text": "Trust the grind." },
    { "id": 89, "text": "Consistency transforms ambition into achievement." },
    { "id": 90, "text": "Your focus determines your results." },

    { "id": 91, "text": "Build today what you want tomorrow." },
    { "id": 92, "text": "Effort compounds like interest." },
    { "id": 93, "text": "Your drive defines your destination." },
    { "id": 94, "text": "Big goals require daily discipline." },
    { "id": 95, "text": "Stay focused, stay humble." },
    { "id": 96, "text": "Your work ethic shapes your success." },
    { "id": 97, "text": "Persistence beats talent when talent quits." },
    { "id": 98, "text": "Train your mind before your body." },
    { "id": 99, "text": "Discipline is doing what must be done." },
    { "id": 100, "text": "Your future self depends on your present self." },

    { "id": 101, "text": "Stay committed to your growth." },
    { "id": 102, "text": "Effort today makes life easier tomorrow." },
    { "id": 103, "text": "Strong habits create strong results." },
    { "id": 104, "text": "Each small step moves you forward." },
    { "id": 105, "text": "Growth requires patience and persistence." },
    { "id": 106, "text": "Your journey matters as much as your destination." },
    { "id": 107, "text": "Consistency is quiet but powerful." },
    { "id": 108, "text": "Your vision fuels your discipline." },
    { "id": 109, "text": "Progress is earned daily." },
    { "id": 110, "text": "Every focused effort brings you closer." }
  ]
}
